qbitshield/__init__.py
qbitshield/client.py
qbitshield-2.0.2.dist-info/METADATA
qbitshield-2.0.2.dist-info/WHEEL
qbitshield-2.0.2.dist-info/top_level.txt
qbitshield-2.0.2.dist-info/RECORD
